{
	"points":[
		{

			"pointId":99991001,
			"desc":"首次分享",
			"reward":{
				"content":{
					"randoms":[
						{
							"weight":2500,
							"items":[
								{
									"stop":2000,
									"start":300,
									"itemId":"user:chip"
								}
							],
							"typeId":"FixedContent"
						},
						{
							"weight":3500,
							"items":[
								{
									"stop":5000,
									"start":2000,
									"itemId":"user:chip"
								}
							],
							"typeId":"FixedContent"
						},
						{
							"weight":1000,
							"items":[
								{
									"count":2,
									"itemId":"item:2003"
								}
							],
							"typeId":"FixedContent"
						},
						{
							"weight":500,
							"items":[
								{
									"count":3,
									"itemId":"item:3002"
								}
							],
							"typeId":"FixedContent"
						},
						{
							"weight":500,
							"items":[
								{
									"count":5,
									"itemId":"item:1007"
								}
							],
							"typeId":"FixedContent"
						},
						{
							"weight":1999,
							"items":[
								{
									"stop":5151,
									"start":5151,
									"itemId":"user:chip"
								}
							],
							"typeId":"FixedContent"
						},
						{
							"weight":1,
							"items":[
								{
									"count":1,
									"itemId":"item:3001"
								}
							],
							"typeId":"FixedContent"
						}
					],
					"typeId":"RandomContent"
				},
				"cycle":{
					"timeCycle":{
						"typeId":"day"
					},
					"count":-1
				}
			},
			"contents":[
				[
					99992001,
					1
				]
			]
		},
		{
			"pointId":99991002,
			"desc":"每日分享",
			"reward":{
				"content":{
					"typeId":"FixedContent",
					"items":[
						{
							"itemId":"user:chip",
							"count":1000
						}
					]
				},
				"cycle":{
					"timeCycle":{
						"typeId":"day"
					},
					"count":1
				}
			},
			"contents":[
				[
					99992002,
					1
				]
			]
		},
		{
			"pointId":6102,
			"desc":"连胜分享",
			"reward":{
				"content":{
					"typeId":"FixedContent",
					"items":[
						{
							"itemId":"item:2003",
							"count":1
						}
					]
				},
				"cycle":{
					"timeCycle":{
						"typeId":"day"
					},
					"count":1
				}
			},
			"contents":[
				[
					66663,
					1
				]
			]
		},
		{
			"pointId":6103,
			"desc":"赢牌分享",
			"reward":{
				"content":{
					"typeId":"FixedContent",
					"items":[
						{
							"itemId":"item:2003",
							"count":1
						}
					]
				},
				"cycle":{
					"timeCycle":{
						"typeId":"day"
					},
					"count":1
				}
			},
			"contents":[
				[
					66664,
					1
				]
			]
		},
		{
			"pointId":6105,
			"desc":"实物赛分享",
			"reward":{
				"content":{
					"typeId":"FixedContent",
					"items":[
						{
							"itemId":"item:1008",
							"count":1
						}
					]
				},
				"cycle":{
					"timeCycle":{
						"typeId":"day"
					},
					"count":1
				}
			},
			"contents":[
				[
					66662,
					1
				]
			]
		},
		{
			"pointId":6104,
			"desc":"红包赛分享",
			"reward":{
				"content":{
					"typeId":"FixedContent",
					"items":[
						{
							"itemId":"item:3129",
							"count":1
						}
					]
				},
				"cycle":{
					"timeCycle":{
						"typeId":"day"
					},
					"count":1
				}
			},
			"contents":[
				[
					666610,
					1
				]
			]
		},
		{
			"pointId":999901041,
			"desc":"2000万红包主要邀请",
			"contents":[
				[
					99996516,
					1
				]
			]
		},
		{
			"pointId":999901042,
			"desc":"2000万红包提醒",
			"contents":[
				[
					99996516,
					1
				]
			]
		},		
		{
			"pointId":999901044,
			"desc":"红包雨分享",
			"contents":[
				[
					99996520,
					1
				]
			]
		},
		{
			"pointId":999901046,
			"desc":"2000万红包主要邀请-ios",
			"contents":[
				[
					99996516,
					1
				]
			]
		},		
		{
			"pointId":999901047,
			"desc":"2000万红包提醒-ios",
			"contents":[
				[
					99996516,
					1
				]
			]
		},
		{
			"pointId":999999999,
			"desc":"热点分享-美好生活",
			"contents":[
				[
					99999993,
					1
				],
				[
					99999994,
					1
				]					
			]
		},
		{
			"pointId":999991048,
			"desc":"38妇女节",
			"contents":[
				[
					99999994,
					1
				]			
			]
		},
		{
			"pointId":67890000,
			"desc":"富豪斗地主分享奖励",
			"reward":{
				"content":{
					"typeId":"FixedContent",
					"items":[
						{
							"itemId":"item:1311",
							"count":1
						}
					]
				},
				"cycle":{
					"timeCycle":{
						"typeId":"day"
					},
					"count":1
				}
			},
			"contents":[
				[
					67890001,
					1
				]				
			]
		},
		{
			"pointId":67890001,
			"desc":"富豪斗地主每日失败后，复活专用分享",
			"reward":{
				"content":{
					"typeId":"FixedContent",
					"items":[
						{
							"itemId":"item:1311",
							"count":1
						}
					]
				},
				"cycle":{
					"timeCycle":{
						"typeId":"day"
					},
					"count":5
				}
			},
			"contents":[
				[
					67890001,
					1
				]
			]
		},
		{
			"pointId":67890002,
			"desc":"每日分享三个不同群",
			"reward":{
				"content":{
					"typeId":"FixedContent",
					"items":[
						{
							"itemId":"item:1311",
							"count":1
						}
					]
				},
				"cycle":{
					"timeCycle":{
						"typeId":"day"
					},
					"count":3
				}
			},
			"contents":[
				[
					67890001,
					1
				]
			]
		},
		{
			"pointId":67890003,
			"desc":"通关后分享",
			"reward":{
				"content":{
					"typeId":"FixedContent",
					"items":[
						{
							"itemId":"item:1311",
							"count":1
						}
					]
				},
				"cycle":{
					"timeCycle":{
						"typeId":"day"
					},
					"count":5
				}
			},
			"contents":[
				[
					67890001,
					1
				]
			]
		},
		{
			"pointId":67890004,
			"desc":"提现后分享",
			"reward":{
				"content":{
					"typeId":"FixedContent",
					"items":[
						{
							"itemId":"item:1311",
							"count":1
						}
					]
				},
				"cycle":{
					"timeCycle":{
						"typeId":"day"
					},
					"count":5
				}
			},
			"contents":[
				[
					67890001,
					1
				]
			]
		},
		{
			"pointId":66660001,
			"desc":"途游微信小程序",
			"reward":{
				"content":{
					"typeId":"FixedContent",
					"items":[
						{
							"itemId":"user:chip",
							"count":20
						}
					]
				},
				"cycle":{
					"timeCycle":{
						"typeId":"day"
					},
					"count":10
				}
			},
			"contents":[
				[
					66660001,
					1
				]
			]
		},
		{
			"pointId":66660002,
			"desc":"途游微信小程序",
			"reward":{
				"content":{
					"typeId":"FixedContent",
					"items":[
						{
							"itemId":"user:chip",
							"count":50
						}
					]
				},
				"cycle":{
					"timeCycle":{
						"typeId":"day"
					},
					"count":10
				}
			},
			"contents":[
				[
					66660001,
					1
				]
			]
		},
		{
			"pointId":66660003,
			"desc":"途游微信小程序",
			"reward":{
				"content":{
					"typeId":"FixedContent",
					"items":[
						{
							"itemId":"user:chip",
							"count":90
						}
					]
				},
				"cycle":{
					"timeCycle":{
						"typeId":"day"
					},
					"count":10
				}
			},
			"contents":[
				[
					66660001,
					1
				]
			]
		},
		{
			"pointId":66660004,
			"desc":"途游微信小程序",
			"reward":{
				"content":{
					"typeId":"FixedContent",
					"items":[
						{
							"itemId":"user:chip",
							"count":150
						}
					]
				},
				"cycle":{
					"timeCycle":{
						"typeId":"day"
					},
					"count":10
				}
			},
			"contents":[
				[
					66660001,
					1
				]
			]
		},
		{
			"pointId":66660005,
			"desc":"途游微信小程序",
			"reward":{
				"content":{
					"typeId":"FixedContent",
					"items":[
						{
							"itemId":"user:chip",
							"count":220
						}
					]
				},
				"cycle":{
					"timeCycle":{
						"typeId":"day"
					},
					"count":10
				}
			},
			"contents":[
				[
					66660001,
					1
				]
			]
		},
		{
			"pointId":66660006,
			"desc":"途游微信小程序",
			"reward":{
				"content":{
					"typeId":"FixedContent",
					"items":[
						{
							"itemId":"user:chip",
							"count":320
						}
					]
				},
				"cycle":{
					"timeCycle":{
						"typeId":"day"
					},
					"count":10
				}
			},
			"contents":[
				[
					66660001,
					1
				]
			]
		},
		{
			"pointId":66660007,
			"desc":"途游微信小程序",
			"reward":{
				"content":{
					"typeId":"FixedContent",
					"items":[
						{
							"itemId":"user:chip",
							"count":340
						}
					]
				},
				"cycle":{
					"timeCycle":{
						"typeId":"day"
					},
					"count":10
				}
			},
			"contents":[
				[
					66660001,
					1
				]
			]
		},
		{
			"pointId":66660008,
			"desc":"途游微信小程序",
			"reward":{
				"content":{
					"typeId":"FixedContent",
					"items":[
						{
							"itemId":"user:chip",
							"count":430
						}
					]
				},
				"cycle":{
					"timeCycle":{
						"typeId":"day"
					},
					"count":10
				}
			},
			"contents":[
				[
					66660001,
					1
				]
			]
		},
		{
			"pointId":66660009,
			"desc":"途游微信小程序",
			"reward":{
				"content":{
					"typeId":"FixedContent",
					"items":[
						{
							"itemId":"user:chip",
							"count":540
						}
					]
				},
				"cycle":{
					"timeCycle":{
						"typeId":"day"
					},
					"count":10
				}
			},
			"contents":[
				[
					66660001,
					1
				]
			]
		},
		{
			"pointId":66660010,
			"desc":"途游微信小程序",
			"reward":{
				"content":{
					"typeId":"FixedContent",
					"items":[
						{
							"itemId":"user:chip",
							"count":660
						}
					]
				},
				"cycle":{
					"timeCycle":{
						"typeId":"day"
					},
					"count":10
				}
			},
			"contents":[
				[
					66660001,
					1
				]
			]
		},
		{
			"pointId":66660011,
			"desc":"途游微信小程序",
			"reward":{
				"content":{
					"typeId":"FixedContent",
					"items":[
						{
							"itemId":"user:chip",
							"count":780
						}
					]
				},
				"cycle":{
					"timeCycle":{
						"typeId":"day"
					},
					"count":10
				}
			},
			"contents":[
				[
					66660001,
					1
				]
			]
		},
		{
			"pointId":66660012,
			"desc":"途游微信小程序",
			"reward":{
				"content":{
					"typeId":"FixedContent",
					"items":[
						{
							"itemId":"user:chip",
							"count":820
						}
					]
				},
				"cycle":{
					"timeCycle":{
						"typeId":"day"
					},
					"count":10
				}
			},
			"contents":[
				[
					66660001,
					1
				]
			]
		},
		{
			"pointId":66660013,
			"desc":"途游微信小程序",
			"reward":{
				"content":{
					"typeId":"FixedContent",
					"items":[
						{
							"itemId":"user:chip",
							"count":910
						}
					]
				},
				"cycle":{
					"timeCycle":{
						"typeId":"day"
					},
					"count":10
				}
			},
			"contents":[
				[
					66660001,
					1
				]
			]
		},
		{
			"pointId":66660014,
			"desc":"途游微信小程序",
			"reward":{
				"content":{
					"typeId":"FixedContent",
					"items":[
						{
							"itemId":"user:chip",
							"count":1050
						}
					]
				},
				"cycle":{
					"timeCycle":{
						"typeId":"day"
					},
					"count":10
				}
			},
			"contents":[
				[
					66660001,
					1
				]
			]
		},
		{
			"pointId":66660015,
			"desc":"途游微信小程序",
			"reward":{
				"content":{
					"typeId":"FixedContent",
					"items":[
						{
							"itemId":"user:chip",
							"count":1200
						}
					]
				},
				"cycle":{
					"timeCycle":{
						"typeId":"day"
					},
					"count":10
				}
			},
			"contents":[
				[
					66660001,
					1
				]
			]
		},
		{
			"pointId":66660016,
			"desc":"途游微信小程序",
			"reward":{
				"content":{
					"typeId":"FixedContent",
					"items":[
						{
							"itemId":"user:chip",
							"count":1360
						}
					]
				},
				"cycle":{
					"timeCycle":{
						"typeId":"day"
					},
					"count":10
				}
			},
			"contents":[
				[
					66660001,
					1
				]
			]
		},
		{
			"pointId":66661001,
			"desc":"微信小程序朋友桌邀请",
			"reward":{
				"content":{
					"typeId":"FixedContent",
					"items":[
						{
							"itemId":"user:chip",
							"count":100
						}
					]
				},
				"cycle":{
					"timeCycle":{
						"typeId":"day"
					},
					"count":3
				}
			},
			"contents":[
				[
					66660001,
					1
				]
			]
		},
		{
			"pointId":66661002,
			"desc":"微信小程序朋友桌结算",
			"reward":{
				"content":{
					"typeId":"FixedContent",
					"items":[
						{
							"itemId":"user:chip",
							"count":100
						}
					]
				},
				"cycle":{
					"timeCycle":{
						"typeId":"day"
					},
					"count":3
				}
			},
			"contents":[
				[
					66660001,
					1
				]
			]
		},
		{
			"pointId":66662001,
			"desc":"微信小程序红包赛奖励1",
			"reward":{
				"content":{
					"typeId":"FixedContent",
					"items":[
						{
							"itemId":"user:coupon",
							"count":20
						}
					]
				},
				"cycle":{
					"timeCycle":{
						"typeId":"day"
					},
					"count":2
				}
			},
			"contents":[
				[
					66660001,
					1
				]
			]
		},
		{
			"pointId":66662002,
			"desc":"微信小程序红包赛奖励2",
			"reward":{
				"content":{
					"typeId":"FixedContent",
					"items":[
						{
							"itemId":"user:diamond",
							"count":2
						}
					]
				},
				"cycle":{
					"timeCycle":{
						"typeId":"day"
					},
					"count":2
				}
			},
			"contents":[
				[
					66660001,
					1
				]
			]
		}
	],
	"contents":[
		{
			"shareId":99992001,
			"desc":"首次分享",
			"url":"http://3g.tuyoo.com/",
			"shareMethod":"url",
			"whereToShare":[
				"friend",
				"circleOfFriends"
			],
			"isPreview":1,
			"preview":{
				"pURL":"${http_download}/hall/ads/imgs/hall_nopack_share_vert1.jpg",
				"rewardDesc":"分享得100金币",
				"rewardUrl":"${http_download}/hall/roulette/roulette_new_8.png",
				"direction":"vertical"
			},
			"shareRule":{
				"title":"test1",
				"desc":"test2",
				"iconUrl":"${http_download}/hall/roulette/roulette_new_8.png"
			}
		},
		{
			"shareId":99992002,
			"desc":"每日分享",
			"url":"https://3g.tuyoo.com/html/ddznew/ddz/redp.html",
			"shareMethod":"url",
			"whereToShare":[
				"friend"
			],
			"channels":[
				""
			],
			"isPreview":1,
			"preview":{
				"pURL":"${http_download}/hall/ads/imgs/hall_nopack_share_hori1.jpg",
				"rewardDesc":"每日首次分享得金币×1000",
				"rewardUrl":"${http_download}/hall/pdt/imgs/goods_t300k.png",
				"direction":"horizontal"
			},
			"shareRule":{
				"title":"我正在玩【途游斗地主】天天赢话费，跟我一起来吧！",
				"desc":"【途游斗地主】玩法正宗，免房卡免钻石，快来战！",
				"iconUrl":"${http_download}/hall/promote/imgs/share_icon_hongbao2_new.png"
			}
		},
		{
			"shareId":66661,
			"desc":"红包赛分享-图",
			"url":"http://3g.tuyoo.com/html/ddznew/ddz/rp_blank.html",
			"shareMethod":"screenshot",
			"whereToShare":[
				"circleOfFriends"
			],
			"channels":[
			],
			"isPreview":0,
			"shareRule":{
				"sharePicUrl":"${http_download}/hall/ads/imgs/ads_ddz_yaoqianshu_0622_2.jpg"
			},
			"shareQR":{
				"useSystemShare":1,
				"QRsize":140,
				"QRopaque":false,
				"QRicon":"",
				"QRposition":[
					 235,
          			 52
				]
			}
		},
		{
			"shareId":666610,
			"desc":"红包赛分享-链接",
			"url":"http://3g.tuyoo.com/html/ddznew/ddz/rp_blank.html",
			"shareMethod":"url",
			"whereToShare":[
				"friend"
			],
			"channels":[
				""
			],
			"isPreview":0,
			"shareRule":{
				"title":"斗地主赢话费，我又拿奖了！",
				"desc":"快来《途游斗地主》跟我一起赢话费抢红包吧~ 每日还有iPhone X、液晶电视等大奖等你来拿！",
				"iconUrl":"${http_download}/hall/promote/imgs/share_icon_hongbao2_new.png"
			}
		},		
		{
			"shareId":66662,
			"desc":"家电赛分享",
			"url":"http://3g.tuyoo.com/html/ddznew/ddz/hh_blank.html",
			"shareMethod":"screenshot",
			"whereToShare":[
				"circleOfFriends"
			],
			"channels":[
			],
			"isPreview":0,
			"shareRule":{
				"sharePicUrl":"${http_download}/hall/ads/imgs/ads_ddz_yaoqianshu_0622_2.jpg"
			},
			"shareQR":{
				"useSystemShare":1,
				"QRsize":100,
				"QRopaque":true,
				"QRicon":"",
				"QRposition":[
					75.3,
					160.8
				]
			}
		},
		{
			"shareId":66663,
			"desc":"金币桌连胜分享",
			"url":"http://3g.tuyoo.com/html/ddznew/ddz/win.html",
			"shareMethod":"screenshot",
			"whereToShare":[
				"circleOfFriends"
			],
			"channels":[
			],
			"isPreview":0,
			"shareRule":{
				"sharePicUrl":"${http_download}/hall/ads/imgs/ads_ddz_yaoqianshu_0622_2.jpg"
			},
			"shareQR":{
				"useSystemShare":1,
				"QRsize":100,
				"QRopaque":true,
				"QRicon":"",
				"QRposition":[
					75.3,
					160.8
				]
			}
		},
		{
			"shareId":66664,
			"desc":"金币桌赢牌分享",
			"url":"http://3g.tuyoo.com/html/ddznew/ddz/gold.html",
			"shareMethod":"screenshot",
			"whereToShare":[
				"circleOfFriends"
			],
			"channels":[
			],
			"isPreview":0,
			"shareRule":{
				"sharePicUrl":"${http_download}/hall/ads/imgs/ads_ddz_yaoqianshu_0622_2.jpg"
			},
			"shareQR":{
				"useSystemShare":1,
				"QRsize":100,
				"QRopaque":true,
				"QRicon":"",
				"QRposition":[
					75.3,
					160.8
				]
			}
		},
		{
			"shareId":99996516,
			"desc":"2000万红包主要邀请-链接",
			"url":"https://3g.tuyoo.com/html/ddznew/dZhuInvite/dZhuInvite.html",
			"shareMethod":"url",
			"whereToShare":[
				"friend"
			],
			"channels":[
				""
			],
			"isPreview":0,
			"shareRule":{
				"title":"斗地主赢米面油 生活更美好",
				"desc":"20万份粮油大米免费赠送，活动详情点击查看！",
				"iconUrl":"${http_download}/hall/promote/imgs/icon_goodlife.png",
				"sharePicUrl":"${http_download}/dizhu/share/share_goodlife.jpg"
			},
			"shareQR":{
			    "useSystemShare":0,
				"doNothing":0,
				"QRsize":135,
				"QRopaque":false,
				"QRicon":"",
				"QRposition":[
					253,
					120
				],
				"identityFontSize":45,
				"identityFontColor":[176,14,11],
				"identityAnchor":[0.5,0.5],
				"identityPos":[320,400]				
			}
		},
		{
			"shareId":99996526,
			"desc":"2000万红包主要邀请-图-文案1",
			"url":"https://3g.tuyoo.com/html/ddznew/dZhuInvite/dZhuInvite.html",
			"shareMethod":"png",
			"whereToShare":[
				"circleOfFriends"
			],
			"channels":[
				""
			],
			"isPreview":0,
			"preview":{
				"pURL":"${http_download}/hall/ads/imgs/hall_nopack_share_hori.png",
				"rewardDesc":"成功邀请1位好友奖励2元",
				"rewardUrl":"${http_download}/hall/pdt/imgs/goods_t300k.png",
				"direction":"horizontal"
			},
			"shareRule":{
				"title":" ",
				"desc":"这个真能领红包！快行动\n先扫码下《途游斗地主》登录直接送0.8元 \n游戏里点右上角的拜年红包 \n每邀请1个好友奖励3元",
				"iconUrl":"${http_download}/hall/promote/imgs/share_icon_hongbao2_new.png",
				"sharePicUrl":"${http_download}/dizhu/share/share_2000_180130.jpg"
			},
			"shareQR":{
			    "useSystemShare":1,
				"doNothing":0,
				"QRsize":135,
				"QRopaque":false,
				"QRicon":"",
				"QRposition":[
					253,
					120
				],
				"identityFontSize":45,
				"identityFontColor":[176,14,11],
				"identityAnchor":[0.5,0.5],
				"identityPos":[320,400]				
			}
		},
		{
			"shareId":99996536,
			"desc":"2000万红包主要邀请-图-文案2",
			"url":"https://3g.tuyoo.com/html/ddznew/dZhuInvite/dZhuInvite.html",
			"shareMethod":"png",
			"whereToShare":[
				"circleOfFriends"
			],
			"channels":[
				""
			],
			"isPreview":0,
			"preview":{
				"pURL":"${http_download}/hall/ads/imgs/hall_nopack_share_hori.png",
				"rewardDesc":"成功邀请1位好友奖励2元",
				"rewardUrl":"${http_download}/hall/pdt/imgs/goods_t300k.png",
				"direction":"horizontal"
			},
			"shareRule":{
				"title":" ",
				"desc":"天呐~扫码免费抢红包！\n总计2000万 每天秒杀各种年货~\n参与方法如下：\n  1.扫码进入活动页面\n  2.点击【复制】并下载《途游斗地主》\n  3.进入游戏立即参与活动",
				"iconUrl":"${http_download}/hall/promote/imgs/share_icon_hongbao2_new.png",
				"sharePicUrl":"${http_download}/dizhu/share/share_2000_180130.jpg"
			},
			"shareQR":{
			    "useSystemShare":1,
				"doNothing":0,
				"QRsize":135,
				"QRopaque":false,
				"QRicon":"",
				"QRposition":[
					253,
					120
				],
				"identityFontSize":45,
				"identityFontColor":[176,14,11],
				"identityAnchor":[0.5,0.5],
				"identityPos":[320,400]				
			}
		},		
		{
			"shareId":99996517,
			"desc":"2000万红包提醒-链接",
			"url":"https://3g.tuyoo.com/html/ddznew/dZhuInvite/dZhuInvite.html",
			"shareMethod":"url",
			"whereToShare":[
				"friend"
			],
			"channels":[
				""
			],
			"isPreview":0,
			"preview":{
				"pURL":"${http_download}/hall/ads/imgs/hall_nopack_share_hori.png",
				"rewardDesc":"成功邀请1位好友奖励3元",
				"rewardUrl":"${http_download}/hall/pdt/imgs/goods_t300k.png",
				"direction":"horizontal"
			},
			"shareRule":{
				"title":"您有未读消息2条",
				"desc":"【途游斗地主】提醒您登录游戏查看",
				"iconUrl":"${http_download}/hall/promote/imgs/share_icon_hongbao2_new.png",
				"sharePicUrl":"${http_download}/dizhu/share/share_2000_180130.jpg"
			},
			"shareQR":{
			    "useSystemShare":0,
				"doNothing":0,
				"QRsize":135,
				"QRopaque":false,
				"QRicon":"",
				"QRposition":[
					253,
					120
				],
				"identityFontSize":45,
				"identityFontColor":[176,14,11],
				"identityAnchor":[0.5,0.5],
				"identityPos":[320,400]				
			}
		},
		{
			"shareId":99996527,
			"desc":"2000万红包提醒-图",
			"url":"https://3g.tuyoo.com/html/ddznew/dZhuInvite/dZhuInvite.html",
			"shareMethod":"png",
			"whereToShare":[
				"friend"
			],
			"channels":[
				""
			],
			"isPreview":0,
			"preview":{
				"pURL":"${http_download}/hall/ads/imgs/hall_nopack_share_hori.png",
				"rewardDesc":"成功邀请1位好友奖励2元",
				"rewardUrl":"${http_download}/hall/pdt/imgs/goods_t300k.png",
				"direction":"horizontal"
			},
			"shareRule":{
				"title":" ",
				"desc":"2018新春活动开启重磅福利！\\n玩途游斗地主瓜分2000万红包！",
				"iconUrl":"${http_download}/hall/promote/imgs/share_icon_hongbao2_new.png",
				"sharePicUrl":"${http_download}/dizhu/share/share_2000_180130.jpg"
			},
			"shareQR":{
			    "useSystemShare":1,
				"doNothing":0,
				"QRsize":135,
				"QRopaque":false,
				"QRicon":"",
				"QRposition":[
					253,
					120
				],
				"identityFontSize":45,
				"identityFontColor":[176,14,11],
				"identityAnchor":[0.5,0.5],
				"identityPos":[320,400]				
			}
		},	
		{
			"shareId":99996520,
			"desc":"红包雨分享",
			"url":"http://3g.tuyoo.com/html/ddznew/ddz/rp_rain.html",
			"shareMethod":"png",
			"whereToShare":[
				"circleOfFriends"
			],
			"channels":[
			],
			"isPreview":0,
			"preview":{
				"pURL":"${http_download}/hall/act/imgs/yuandan1.jpg",
				"rewardDesc":"分享后下次红包雨必中",
				"rewardUrl":"${http_download}/hall/roulette/roulette_new_8.png",
				"direction":"vertical"
			},
			"shareRule":{
				"sharePicUrl":"${http_download}/dizhu/share/share_hongbaoyu_180211_2.jpg"
			},
			"shareQR":{
				"useSystemShare":1,
				"QRsize":170,
				"QRopaque":true,
				"QRicon":"",
				"QRposition":[
					238,
					83
				],
				"couponFontSize":120,
				"couponFontColor":[255,243,110],
				"couponAnchor":[1,0.5],				
				"couponPos":[415,360]
			}
		},
		{
			"shareId":99999991,
			"desc":"热点分享-春运回家-文案1",
			"url":"https://3g.tuyoo.com/html/ddznew/dZhuInvite/dZhuInvite.html",
			"shareMethod":"png",
			"whereToShare":[
				"circleOfFriends"
			],
			"channels":[
				""
			],
			"isPreview":0,
			"shareRule":{
				"title":" ",
				"desc":"吃了整整一年外卖\n回家的路上睡着了\n梦里全是妈妈烧的菜",
				"iconUrl":"${http_download}/hall/promote/imgs/share_icon_hongbao2_new.png",
				"sharePicUrl":"${http_download}/dizhu/share/share_news_180211.jpg"
			},
			"shareQR":{
			    "useSystemShare":1,
				"doNothing":1,
				"QRsize":135,
				"QRopaque":false,
				"QRicon":"",
				"QRposition":[
					253,
					120
				],
				"identityFontSize":45,
				"identityFontColor":[176,14,11],
				"identityAnchor":[0.5,0.5],
				"identityPos":[320,400]				
			}
		},
		{
			"shareId":99999992,
			"desc":"热点分享-春运回家-文案2",
			"url":"https://3g.tuyoo.com/html/ddznew/dZhuInvite/dZhuInvite.html",
			"shareMethod":"png",
			"whereToShare":[
				"circleOfFriends"
			],
			"channels":[
				""
			],
			"isPreview":0,
			"shareRule":{
				"title":" ",
				"desc":"我的远方是故乡",
				"iconUrl":"${http_download}/hall/promote/imgs/share_icon_hongbao2_new.png",
				"sharePicUrl":"${http_download}/dizhu/share/share_news_180211.jpg"
			},
			"shareQR":{
			    "useSystemShare":1,
				"doNothing":1,
				"QRsize":135,
				"QRopaque":false,
				"QRicon":"",
				"QRposition":[
					253,
					120
				],
				"identityFontSize":45,
				"identityFontColor":[176,14,11],
				"identityAnchor":[0.5,0.5],
				"identityPos":[320,400]				
			}
		},
		{
			"shareId":99999993,
			"desc":"美好生活发福利-链接",
			"url":"http://3g.tuyoo.com/html/LandingPage/singlePage/ddz/ddzgroup/sweet.html",
			"shareMethod":"url",
			"whereToShare":[
				"friend"
			],
			"channels":[
				""
			],
			"isPreview":0,
			"shareRule":{
				"title":" 美好生活徐豆豆给您发福利啦",
				"desc":"斗地主赢米油 生活更美好",
				"iconUrl":"${http_download}/dizhu/room/imgs/goodlifefriend.jpg",
				"sharePicUrl":"${http_download}/dizhu/share/share_2000_180130.jpg"
			}			
		},
		{
			"shareId":99999994,
			"desc":"美好生活不知道-链接",
			"url":"http://3g.tuyoo.com/html/LandingPage/singlePage/ddz/ddzgroup/sweetSiter.html",
			"shareMethod":"url",
			"whereToShare":[
				"friend"
			],
			"channels":[
				""
			],
			"isPreview":0,
			"shareRule":{
				"title":"什么是中国式美好生活？99%的人都不知道！",
				"desc":"斗地主赢米油 生活更美好",
				"iconUrl":"${http_download}/dizhu/room/imgs/goodlifefriend.jpg",
				"sharePicUrl":"${http_download}/hall/promote/imgs/share_3.8funvjie.jpg"
			}
		},
		{
			"shareId":67890001,
			"desc":"富豪斗地主小游戏邀请",
			"url":"https://3g.tuyoo.com/",
			"shareMethod":"url",
			"whereToShare":[
				"friend"
			],
			"channels":[
				""
			],
			"isPreview":0,
			"preview":{
				"pURL":"${http_download}/hall/ads/imgs/hall_nopack_share_hori.png",
				"rewardDesc":"每日首次分享得1钻石",
				"rewardUrl":"${http_download}/hall/pdt/imgs/goods_t300k.png",
				"direction":"horizontal"
			},
			"shareRule":{
				"title":"我正在玩【富豪斗地主】天天赢话费，跟我一起来吧！",
				"desc":"【富豪斗地主】玩法正宗，闯关赢红包，快来战！",
				"iconUrl":"${http_download}/hall/promote/imgs/share_icon_hongbao2_new.png"
			}
		},
		{
			"shareId":66660001,
			"desc":"斗地主微信小程序",
			"url":"https://3g.tuyoo.com/",
			"shareMethod":"url",
			"whereToShare":[
				"friend"
			],
			"channels":[
				""
			],
			"isPreview":0,
			"preview":{
				"pURL":"${http_download}/hall/ads/imgs/hall_nopack_share_hori.png",
				"rewardDesc":"每日首次分享得1钻石",
				"rewardUrl":"${http_download}/hall/pdt/imgs/goods_t300k.png",
				"direction":"horizontal"
			},
			"shareRule":{
				"title":"我正在玩【途游都地租】天天赢话费，跟我一起来吧！",
				"desc":"【途游都地租】玩法正宗，赢红包，快来战！",
				"iconUrl":"${http_download}/hall/promote/imgs/share_icon_hongbao2_new.png"
			}
		}
	]
}