{
  "buyinchip": 500000,
  "dummyUserCount": 0,
  "gameRule": "classic",
  "hasrobot": 1,
  "iscreate": 0,
  "create_item": 6013,
  "ismatch": 0,
  "level": "middle",
  "matchConf": null,
  "maxCoin": -1,
  "maxCoinQS": -1,
  "maxLevel": -1,
  "minCoin": 300000,
  "minCoinQS": 300000,
  "base_chip": 10000,
  "service_fee_sit_down": 5000,
  "service_fee_win": 0,
  "service_fee_lose": 0,
  "service_fee_dahu_rate":0,
  "service_fee_dahu_on":0.5,
  "service_fee_dahu_fan":16,
  "name": "高级场",
  "playMode": "zhuoji",
  "playModeName": "捉鸡",
  "taskDesc": "玩3局送0.25红包券",
  "tableType": "normal",
  "tableConf": {
    "robotLevel": 1,
    "autoLevel": 0,
    "base_chip": 10000,
    "big_degree_fee": [],
    "create_user_score": 0,
    "good_tile_chance": 0.5,
    "leave_vote_num": {
      "4": 4
    },
    "refuse_leave_vote_num": {
      "4": 1
    },
    "maxWinNum": 3,
    "maxSeatN": 4,
    "play_timeout": 8,
    "room_coefficient": 1,
    "service_fee": 5000,
    "trustee_timeout": 0,
    "ready_max_timeout": 3600,
    "ready_after_sit": 1,
    "dissolve_vote_time_out": 60,
    "gang_base": 1,
    "win_base": 1,
    "score_base": 0,
    "max_fan": 0,
    "resume_item_after_begin": 0,
    "tiandihuFan": 1,
    "chat_chip": 500,
    "chat_time": 5,
    "nameDesc": "富裕",
    "taskDesc": "玩3局送0.25红包券"
  },
  "winTasksDesc": {
    "desc": "",
    "winTasks": []
  },
  "typeName": "normal"
}