{
  "room_items" : {
    "jd10" : {
      "id" : 21011,
      "name" : "经典新手场",
      "basebet": 50,
      "mincoin": 0,
      "maxcoin": 10000,
      "entry" : "底注50金币",
      "config" : 0,
      "condition" : "0到1万金币准入",
      "nameurl" : "${http_download}/dizhu/room/imgs/room_name_jdxsc.png"
    },
    "jd20" : {
      "id" : 21012,
      "name" : "经典中级场",
      "basebet": 200,
      "mincoin": 2000,
      "maxcoin": -1,
      "entry" : "底注200金币",
      "config" : 0,
      "condition" : "6局送0.01红包券\n大于2000金币准入",
      "nameurl" : "${http_download}/dizhu/room/imgs/room_name_jdzjc.png"
    },
    "jd30" : {
      "id" : 21013,
      "name" : "经典高级场",
      "basebet": 1000,
      "mincoin": 10000,
      "maxcoin": -1,
      "entry" : "底注1000金币",
      "config" : 0,
      "condition" : "6局送0.02红包券\n大于1万金币准入",
      "nameurl" : "${http_download}/dizhu/room/imgs/room_name_jdgjc.png"
    },
    "jd40" : {
      "id" : 21014,
      "name" : "经典大师场",
      "basebet": 2000,
      "mincoin": 20000,
      "maxcoin": -1,
      "entry" : "底注2000金币",
      "config" : 0,
      "condition" : "6局送0.04红包券\n大于2万金币准入",
      "nameurl" : "${http_download}/dizhu/room/imgs/room_name_jddsc.png"
    },

    "fp10" : {
      "id" : 21021,
      "name" : "放炮新手场",
      "basebet": 50,
      "mincoin": 0,
      "maxcoin": -1,
      "entry" : "底注50金币",
      "config" : 0,
      "condition" : "6局送0.01红包券\n0金币准入",
      "nameurl" : "${http_download}/dizhu/room/imgs/room_name_jdxsc.png"
    },
    "fp20" : {
      "id" : 21022,
      "name" : "放炮中级场",
      "basebet": 200,
      "mincoin": 2000,
      "maxcoin": -1,
      "entry" : "底注200金币",
      "config" : 0,
      "condition" : "6局送0.01红包券\n大于2000金币准入",
      "nameurl" : "${http_download}/dizhu/room/imgs/room_name_jdzjc.png"
    },
    "fp30" : {
      "id" : 21023,
      "name" : "放炮高级场",
      "basebet": 1000,
      "mincoin": 10000,
      "maxcoin": -1,
      "entry" : "底注1000金币",
      "config" : 0,
      "condition" : "6局送0.02红包券\n大于1万金币准入",
      "nameurl" : "${http_download}/dizhu/room/imgs/room_name_jdgjc.png"
    },
    "fp40" : {
      "id" : 21024,
      "name" : "放炮大师场",
      "basebet": 2000,
      "mincoin": 20000,
      "maxcoin": -1,
      "entry" : "底注2000金币",
      "config" : 0,
      "condition" : "6局送0.04红包券\n大于2万金币准入",
      "nameurl" : "${http_download}/dizhu/room/imgs/room_name_jddsc.png"
    },

    "fd10" : {
      "id" : 21031,
      "name" : "亲友新手场",
      "basebet": 200,
      "mincoin": 1000,
      "maxcoin": -1,
      "entry" : "底注200金币",
      "config" : 0,
      "condition" : "跑胡子3级\n大于1000金币准入",
      "nameurl" : "${http_download}/dizhu/room/imgs/room_name_jdxsc.png"
    },
    "fd20" : {
      "id" : 21032,
      "name" : "亲友中级场",
      "basebet": 500,
      "mincoin": 5000,
      "maxcoin": -1,
      "entry" : "底注500金币",
      "config" : 0,
      "condition" : "跑胡子4级\n大于5000金币准入",
      "nameurl" : "${http_download}/dizhu/room/imgs/room_name_jdzjc.png"
    },
    "fd30" : {
      "id" : 21033,
      "name" : "亲友高级场",
      "basebet": 1000,
      "mincoin": 10000,
      "maxcoin": -1,
      "entry" : "底注1000金币",
      "config" : 0,
      "condition" : "跑胡子5级\n大于1万金币准入",
      "nameurl" : "${http_download}/dizhu/room/imgs/room_name_jdgjc.png"
    },
    "fd40" : {
      "id" : 21034,
      "name" : "亲友大师场",
      "basebet": 2000,
      "mincoin": 20000,
      "maxcoin": -1,
      "entry" : "底注2000金币",
      "config" : 0,
      "condition" : "跑胡子6级\n大于2万金币准入",
      "nameurl" : "${http_download}/dizhu/room/imgs/room_name_jddsc.png"
    },
    "p210" : {
      "id" : 21061,
      "name" : "二人新手场",
      "basebet": 50,
      "mincoin": 1000,
      "maxcoin": 5000,
      "entry" : "底注50金币",
      "config" : 0,
      "condition" : "大于500金币准入",
      "nameurl" : "${http_download}/dizhu/room/imgs/room_name_jdxsc.png"
    },
    "p220" : {
      "id" : 21062,
      "name" : "二人中级场",
      "basebet": 200,
      "mincoin": 5000,
      "maxcoin": 10000,
      "entry" : "底注200金币",
      "config" : 0,
      "condition" : "大于2000金币准入",
      "nameurl" : "${http_download}/dizhu/room/imgs/room_name_jdzjc.png"
    },
    "p230" : {
      "id" : 21063,
      "name" : "二人高级场",
      "basebet": 1000,
      "mincoin": 10000,
      "maxcoin": 20000,
      "entry" : "底注1000金币",
      "config" : 0,
      "condition" : "大于1万金币准入",
      "nameurl" : "${http_download}/dizhu/room/imgs/room_name_jdgjc.png"
    },
    "p240" : {
      "id" : 21064,
      "name" : "二人大师场",
      "basebet": 2000,
      "mincoin": 20000,
      "maxcoin": -1,
      "entry" : "底注2000金币",
      "config" : 0,
      "condition" : "大于2万金币准入",
      "nameurl" : "${http_download}/dizhu/room/imgs/room_name_jddsc.png"
    },
    "bmt10" : {
      "id" : 21071,
      "name" : "半名堂新手场",
      "basebet": 50,
      "mincoin": 1000,
      "maxcoin": 5000,
      "entry" : "底注50金币",
      "config" : 0,
      "condition" : "大于500金币准入",
      "nameurl" : "${http_download}/dizhu/room/imgs/room_name_jdxsc.png"
    },
    "bmt20" : {
      "id" : 21072,
      "name" : "半名堂中级场",
      "basebet": 200,
      "mincoin": 5000,
      "maxcoin": 10000,
      "entry" : "底注200金币",
      "config" : 0,
      "condition" : "大于2000金币准入",
      "nameurl" : "${http_download}/dizhu/room/imgs/room_name_jdzjc.png"
    },
    "bmt30" : {
      "id" : 21073,
      "name" : "半名堂高级场",
      "basebet": 1000,
      "mincoin": 10000,
      "maxcoin": 20000,
      "entry" : "底注1000金币",
      "config" : 0,
      "condition" : "大于1万金币准入",
      "nameurl" : "${http_download}/dizhu/room/imgs/room_name_jdgjc.png"
    },
    "bmt40" : {
      "id" : 21074,
      "name" : "半名堂大师场",
      "basebet": 2000,
      "mincoin": 20000,
      "maxcoin": -1,
      "entry" : "底注2000金币",
      "config" : 0,
      "condition" : "大于4万金币准入",
      "nameurl" : "${http_download}/dizhu/room/imgs/room_name_jddsc.png"
    },
    "fan81010" : {
      "id" : 21081,
      "name" : "八十番新手场",
      "basebet": 30,
      "mincoin": 400,
      "maxcoin": 25000,
      "entry" : "底注30金币",
      "config" : 0,
      "condition" : "大于400金币准入",
      "nameurl" : "${http_download}/dizhu/room/imgs/room_name_jdxsc.png"
    },
    "fan81020" : {
      "id" : 21082,
      "name" : "八十番中级场",
      "basebet": 200,
      "mincoin": 2000,
      "maxcoin": 200000,
      "entry" : "底注200金币",
      "config" : 0,
      "condition" : "大于2000金币准入",
      "nameurl" : "${http_download}/dizhu/room/imgs/room_name_jdzjc.png"
    },
    "fan81030" : {
      "id" : 21083,
      "name" : "八十番高级场",
      "basebet": 1000,
      "mincoin": 20000,
      "maxcoin": 400000,
      "entry" : "底注1000金币",
      "config" : 0,
      "condition" : "大于2万金币准入",
      "nameurl" : "${http_download}/dizhu/room/imgs/room_name_jdgjc.png"
    },
    "fan81040" : {
      "id" : 21084,
      "name" : "八十番大师场",
      "basebet": 5000,
      "mincoin": 60000,
      "maxcoin": -1,
      "entry" : "底注5000金币",
      "config" : 0,
      "condition" : "大于6万金币准入",
      "nameurl" : "${http_download}/dizhu/room/imgs/room_name_jddsc.png"
    },
    "guilin10" : {
      "id" : 21091,
      "name" : "桂林新手场",
      "basebet": 50,
      "mincoin": 0,
      "maxcoin": -1,
      "entry" : "底注50金币",
      "config" : 0,
      "condition" : "6局送0.01红包券\n0金币准入",
      "nameurl" : "${http_download}/dizhu/room/imgs/room_name_jdxsc.png"
    },
    "guilin20" : {
      "id" : 21092,
      "name" : "桂林中级场",
      "basebet": 200,
      "mincoin": 2000,
      "maxcoin": -1,
      "entry" : "底注200金币",
      "config" : 0,
      "condition" : "6局送0.01红包券\n大于2000金币准入",
      "nameurl" : "${http_download}/dizhu/room/imgs/room_name_jdzjc.png"
    },
    "guilin30" : {
      "id" : 21093,
      "name" : "桂林高级场",
      "basebet": 1000,
      "mincoin": 10000,
      "maxcoin": -1,
      "entry" : "底注1000金币",
      "config" : 0,
      "condition" : "6局送0.02红包券\n大于1万金币准入",
      "nameurl" : "${http_download}/dizhu/room/imgs/room_name_jdgjc.png"
    },
    "guilin40" : {
      "id" : 21094,
      "name" : "桂林大师场",
      "basebet": 2000,
      "mincoin": 20000,
      "maxcoin": -1,
      "entry" : "底注2000金币",
      "config" : 0,
      "condition" : "6局送0.04红包券\n大于2万金币准入",
      "nameurl" : "${http_download}/dizhu/room/imgs/room_name_jddsc.png"
    },
    "hechi10" : {
      "id" : 21111,
      "name" : "河池新手场",
      "basebet": 50,
      "mincoin": 0,
      "maxcoin": -1,
      "entry" : "底注50金币",
      "config" : 0,
      "condition" : "6局送0.01红包券\n0金币准入",
      "nameurl" : "${http_download}/dizhu/room/imgs/room_name_jdxsc.png"
    },
    "hechi20" : {
      "id" : 21112,
      "name" : "河池中级场",
      "basebet": 200,
      "mincoin": 2000,
      "maxcoin": -1,
      "entry" : "底注200金币",
      "config" : 0,
      "condition" : "6局送0.01红包券\n大于2000金币准入",
      "nameurl" : "${http_download}/dizhu/room/imgs/room_name_jdzjc.png"
    },
    "hechi30" : {
      "id" : 21113,
      "name" : "河池高级场",
      "basebet": 1000,
      "mincoin": 10000,
      "maxcoin": -1,
      "entry" : "底注1000金币",
      "config" : 0,
      "condition" : "6局送0.02红包券\n大于1万金币准入",
      "nameurl" : "${http_download}/dizhu/room/imgs/room_name_jdgjc.png"
    },
    "hechi40" : {
      "id" : 21114,
      "name" : "河池大师场",
      "basebet": 2000,
      "mincoin": 20000,
      "maxcoin": -1,
      "entry" : "底注2000金币",
      "config" : 0,
      "condition" : "6局送0.04红包券\n大于2万金币准入",
      "nameurl" : "${http_download}/dizhu/room/imgs/room_name_jddsc.png"
    },
    "chenzhou10" : {
      "id" : 21121,
      "name" : "郴州新手场",
      "basebet": 50,
      "mincoin": 0,
      "maxcoin": -1,
      "entry" : "底注50金币",
      "config" : 0,
      "condition" : "6局送0.01红包券\n0金币准入",
      "nameurl" : "${http_download}/dizhu/room/imgs/room_name_jdxsc.png"
    },
    "chenzhou20" : {
      "id" : 21122,
      "name" : "郴州中级场",
      "basebet": 200,
      "mincoin": 2000,
      "maxcoin": -1,
      "entry" : "底注200金币",
      "config" : 0,
      "condition" : "6局送0.01红包券\n大于2000金币准入",
      "nameurl" : "${http_download}/dizhu/room/imgs/room_name_jdzjc.png"
    },
    "chenzhou30" : {
      "id" : 21123,
      "name" : "郴州高级场",
      "basebet": 1000,
      "mincoin": 10000,
      "maxcoin": -1,
      "entry" : "底注1000金币",
      "config" : 0,
      "condition" : "6局送0.02红包券\n大于1万金币准入",
      "nameurl" : "${http_download}/dizhu/room/imgs/room_name_jdgjc.png"
    },
    "chenzhou40" : {
      "id" : 21124,
      "name" : "郴州大师场",
      "basebet": 2000,
      "mincoin": 20000,
      "maxcoin": -1,
      "entry" : "底注2000金币",
      "config" : 0,
      "condition" : "6局送0.04红包券\n大于2万金币准入",
      "nameurl" : "${http_download}/dizhu/room/imgs/room_name_jddsc.png"
    },
    "shaozi10" : {
      "id" : 21141,
      "name" : "邵阳新手场",
      "basebet": 50,
      "mincoin": 0,
      "maxcoin": -1,
      "entry" : "底注50金币",
      "config" : 0,
      "condition" : "6局送0.01红包券\n0金币准入",
      "nameurl" : "${http_download}/dizhu/room/imgs/room_name_jdxsc.png"
    },
    "shaozi20" : {
      "id" : 21142,
      "name" : "邵阳中级场",
      "basebet": 200,
      "mincoin": 2000,
      "maxcoin": -1,
      "entry" : "底注200金币",
      "config" : 0,
      "condition" : "6局送0.01红包券\n大于2000金币准入",
      "nameurl" : "${http_download}/dizhu/room/imgs/room_name_jdzjc.png"
    },
    "shaozi30" : {
      "id" : 21143,
      "name" : "邵阳高级场",
      "basebet": 1000,
      "mincoin": 10000,
      "maxcoin": -1,
      "entry" : "底注1000金币",
      "config" : 0,
      "condition" : "6局送0.02红包券\n大于1万金币准入",
      "nameurl" : "${http_download}/dizhu/room/imgs/room_name_jdgjc.png"
    },
    "shaozi40" : {
      "id" : 21144,
      "name" : "邵阳大师场",
      "basebet": 2000,
      "mincoin": 20000,
      "maxcoin": -1,
      "entry" : "底注2000金币",
      "config" : 0,
      "condition" : "玩6局送0.04红包券\n大于2万金币准入",
      "nameurl" : "${http_download}/dizhu/room/imgs/room_name_jddsc.png"
    },
    "zhuzhou10" : {
      "id" : 21161,
      "name" : "碰胡子新手场",
      "basebet": 50,
      "mincoin": 0,
      "maxcoin": -1,
      "entry" : "底注50金币",
      "config" : 0,
      "condition" : "6局送0.01红包券\n0金币准入",
      "nameurl" : "${http_download}/dizhu/room/imgs/room_name_jdxsc.png"
    },
    "zhuzhou20" : {
      "id" : 21162,
      "name" : "碰胡子中级场",
      "basebet": 200,
      "mincoin": 2000,
      "maxcoin": -1,
      "entry" : "底注200金币",
      "config" : 0,
      "condition" : "6局送0.01红包券\n大于2000金币准入",
      "nameurl" : "${http_download}/dizhu/room/imgs/room_name_jdzjc.png"
    },
    "zhuzhou30" : {
      "id" : 21163,
      "name" : "碰胡子高级场",
      "basebet": 1000,
      "mincoin": 10000,
      "maxcoin": -1,
      "entry" : "底注1000金币",
      "config" : 0,
      "condition" : "6局送0.02红包券\n大于1万金币准入",
      "nameurl" : "${http_download}/dizhu/room/imgs/room_name_jdgjc.png"
    },
    "zhuzhou40" : {
      "id" : 21164,
      "name" : "碰胡子大师场",
      "basebet": 2000,
      "mincoin": 20000,
      "maxcoin": -1,
      "entry" : "底注2000金币",
      "config" : 0,
      "condition" : "6局送0.04红包券\n大于2万金币准入",
      "nameurl" : "${http_download}/dizhu/room/imgs/room_name_jddsc.png"
    },
    
    "nuanchun_500" : {
      "id" : 21056,
      "name" : "暖春500元红包赛",
      "least" : 0,
      "entry" : "报名费:1张豪杰卡",
      "config" : 4,
      "condition" : "时长30分",
      "nameurl" : "${http_download}/dizhu/room/imgs/room_name_hlxsc.png",
      "playMode": "常德跑胡子"
    },
    
    
    "mt20" : {
      "id" : 21052,
      "name" : "6元红包赛",
      "least" : 0,
      "entry" : "报名费:免费",
      "config" : 4,
      "condition" : "时长15分",
      "nameurl" : "${http_download}/dizhu/room/imgs/room_name_hlxsc.png",
      "detail": "每10分钟开启一场比赛",
      "playMode": "常德跑胡子"
    },
    "mt30" : {
      "id" : 21055,
      "name" : "18元红包赛",
      "least" : 0,
      "entry" : "报名费:3000金币",
      "config" : 4,
      "condition" : "时长25分",
      "nameurl" : "${http_download}/dizhu/room/imgs/room_name_hlxsc.png",
      "detail": "每1小时开启一场比赛",
      "playMode": "常德跑胡子"
    },
    
    
    "mt40" : {
      "id" : 21054,
      "name" : "50元红包赛",
      "least" : 0,
      "entry" : "报名费:免费",
      "config" : 4,
      "condition" : "时长30分",
      "nameurl" : "${http_download}/dizhu/room/imgs/room_name_hlxsc.png",
      "playMode": "常德跑胡子"
    },
    "mt50" : {
      "id" : 21051,
      "name" : "50元红包赛",
      "least" : 0,
      "entry" : "报名费:免费",
      "config" : 4,
      "condition" : "时长30分",
      "nameurl" : "${http_download}/dizhu/room/imgs/room_name_hlxsc.png",
      "playMode": "常德跑胡子"
    },
    "mt60" : {
      "id" : 21053,
      "name" : "300元红包赛",
      "least" : 0,
      "entry" : "报名费:免费",
      "config" : 4,
      "condition" : "时长30分",
      "nameurl" : "${http_download}/dizhu/room/imgs/room_name_hlxsc.png",
      "playMode": "常德跑胡子"
    }
  },
  "session_items" : {
    "jd" : {
      "session" : "经典场",
      "match" : 0,
      "new" : 0,
      "rooms" : ["jd10", "jd20", "jd30", "jd40"],
      "description" : ["1、最正宗的经典玩法，考验技巧，百玩不腻；"]
    },
    "fangpao" : {
      "session" : "放炮罚",
      "match" : 0,
      "new" : 0,
      "rooms" : ["fp10", "fp20", "fp30", "fp40"],
      "description" : ["1、最正宗的经典玩法，考验技巧，百玩不腻；"]
    },
    "p2" : {
      "session" : "二人场",
      "match" : 0,
      "new" : 0,
      "rooms" : ["p210", "p220", "p230", "p240"],
      "description" : ["1、最正宗的经典玩法，考验技巧，百玩不腻；"]
    },
    "bmt" : {
      "session" : "半名堂",
      "match" : 0,
      "new" : 0,
      "rooms" : ["bmt10", "bmt20", "bmt30", "bmt40"],
      "description" : ["1、最正宗的经典玩法，考验技巧，百玩不腻；"]
    },
    "fan810" : {
      "session" : "八十番",
      "match" : 0,
      "new" : 0,
      "rooms" : ["fan81010", "fan81020", "fan81030", "fan81040"],
      "description" : ["1、最正宗的经典玩法，考验技巧，百玩不腻；"]
    },
    "guilin" : {
      "session" : "桂林字牌",
      "match" : 0,
      "new" : 0,
      "rooms" : ["guilin10", "guilin20", "guilin30", "guilin40"],
      "description" : ["1、最正宗的经典玩法，考验技巧，百玩不腻；"]
    },
    "hechi" : {
      "session" : "河池字牌",
      "match" : 0,
      "new" : 0,
      "rooms" : ["hechi10", "hechi20", "hechi30", "hechi40"],
      "description" : ["1、最正宗的经典玩法，考验技巧，百玩不腻；"]
    },
    "chenzhou" : {
      "session" : "郴州字牌",
      "match" : 0,
      "new" : 0,
      "rooms" : ["chenzhou10", "chenzhou20", "chenzhou30", "chenzhou40"],
      "description" : ["1、最正宗的经典玩法，考验技巧，百玩不腻；"]
    },
    "shaozi" : {
      "session" : "邵阳字牌",
      "match" : 0,
      "new" : 0,
      "rooms" : ["shaozi10", "shaozi20", "shaozi30", "shaozi40"],
      "description" : ["1、最正宗的经典玩法，考验技巧，百玩不腻；"]
    },
    "zhuzhou" : {
      "session" : "株洲碰胡子",
      "match" : 0,
      "new" : 0,
      "rooms" : ["zhuzhou10", "zhuzhou20", "zhuzhou30", "zhuzhou40"],
      "description" : ["1、最正宗的经典玩法，考验技巧，百玩不腻；"]
    },
    "mt" : {
      "session" : "比赛场",
      "match" : 1,
      "new" : 1,
      "rooms" : ["nuanchun_500", "mt60", "mt20",  "mt30", "mt40", "mt50"],
      "description" : ["1、比赛需交报名费（有些为免费），结束后按名次发奖励。", "2、为保证公平，一些比赛隐藏了对手信息。"]
    },
    "friends" : {
      "session" : "亲友场",
      "match" : 0,
      "s_type" : 2,
      "new" : 0,
      "rooms" : ["fd10","fd20","fd30","fd40"],
      "description" : ["1、最正宗的经典玩法，考验技巧，百玩不腻；"]
    }
  },
  "templates" : {
    "default" : ["jd", "fangpao", "mt", "friends", "p2", "bmt", "fan810", "guilin", "hechi", "chenzhou", "shaozi", "zhuzhou"]
  }
}
